{
  "timestamp": "2026-04-17T14:43:20.245703+00:00",
  "plate": "4",
  "plate_name": "D",
  "n_modes": 8,
  "n_carriers": 7,
  "strategy": "variance_risk_premium_classifier",
  "vol_lookback_short": 5,
  "vol_lookback_long": 20,
  "vol_forward": 5,
  "vrp_markup": 1.15,
  "friction_bps": 30,
  "train_window": 120,
  "test_window": 20,
  "symbols": {
    "BTC-USD": {
      "always_sell_1d": {
        "total_ret_pct": 15.791990943110235,
        "annual_ret_pct": 5.71358671300779,
        "sharpe": 4.123480915988987,
        "max_dd_pct": 1.8843308811066866,
        "win_rate_pct": 80.75187969924812,
        "profit_factor": 2.522051447699649,
        "n_days": 665,
        "exposure_pct": 100.0,
        "hold_days": 1
      },
      "always_sell_3d": {
        "total_ret_pct": 15.791990943110235,
        "annual_ret_pct": 5.71358671300779,
        "sharpe": 4.123480915988987,
        "max_dd_pct": 1.8843308811066866,
        "win_rate_pct": 80.75187969924812,
        "profit_factor": 2.522051447699649,
        "n_days": 665,
        "exposure_pct": 100.0,
        "hold_days": 3
      },
      "always_sell_5d": {
        "total_ret_pct": 15.791990943110235,
        "annual_ret_pct": 5.71358671300779,
        "sharpe": 4.123480915988987,
        "max_dd_pct": 1.8843308811066866,
        "win_rate_pct": 80.75187969924812,
        "profit_factor": 2.522051447699649,
        "n_days": 665,
        "exposure_pct": 100.0,
        "hold_days": 5
      },
      "binary_1d": {
        "total_ret_pct": -26.671006762313777,
        "annual_ret_pct": -11.09082312325491,
        "sharpe": -5.496608744464185,
        "max_dd_pct": 26.671006762313777,
        "win_rate_pct": 26.015037593984964,
        "profit_factor": 0.2705316087334956,
        "n_days": 665,
        "exposure_pct": 50.67669172932331,
        "hold_days": 1
      },
      "binary_3d": {
        "total_ret_pct": -9.07272427463257,
        "annual_ret_pct": -3.5399976929421872,
        "sharpe": -2.001667984667162,
        "max_dd_pct": 10.570114338918135,
        "win_rate_pct": 31.57894736842105,
        "profit_factor": 0.5676608217556351,
        "n_days": 665,
        "exposure_pct": 45.26315789473684,
        "hold_days": 3
      },
      "binary_5d": {
        "total_ret_pct": -3.6974691067900967,
        "annual_ret_pct": -1.4175630258136618,
        "sharpe": -0.8560569357373241,
        "max_dd_pct": 6.787042903011889,
        "win_rate_pct": 31.278195488721806,
        "profit_factor": 0.7779747519491355,
        "n_days": 665,
        "exposure_pct": 43.007518796992485,
        "hold_days": 5
      },
      "plate_binary_1d": {
        "total_ret_pct": -26.96842548810643,
        "annual_ret_pct": -11.22764826680126,
        "sharpe": -5.526298110349003,
        "max_dd_pct": 27.366263689897885,
        "win_rate_pct": 26.917293233082706,
        "profit_factor": 0.2724772924489632,
        "n_days": 665,
        "exposure_pct": 52.03007518796993,
        "hold_days": 1
      },
      "plate_binary_3d": {
        "total_ret_pct": -9.07272427463257,
        "annual_ret_pct": -3.5399976929421872,
        "sharpe": -2.001667984667162,
        "max_dd_pct": 10.570114338918135,
        "win_rate_pct": 31.57894736842105,
        "profit_factor": 0.5676608217556351,
        "n_days": 665,
        "exposure_pct": 45.26315789473684,
        "hold_days": 3
      },
      "plate_binary_5d": {
        "total_ret_pct": -4.045371559766508,
        "annual_ret_pct": -1.5526725949814413,
        "sharpe": -0.9259165509383377,
        "max_dd_pct": 7.3448674913613745,
        "win_rate_pct": 32.78195488721805,
        "profit_factor": 0.7666867415363843,
        "n_days": 665,
        "exposure_pct": 45.41353383458647,
        "hold_days": 5
      },
      "plate_vw_1d": {
        "total_ret_pct": -27.464228063268393,
        "annual_ret_pct": -11.45650973789576,
        "sharpe": -6.012955524766519,
        "max_dd_pct": 27.464228063268393,
        "win_rate_pct": 23.909774436090224,
        "profit_factor": 0.21203565615151337,
        "n_days": 665,
        "exposure_pct": 47.81954887218045,
        "hold_days": 1
      },
      "plate_vw_3d": {
        "total_ret_pct": -11.941113027467987,
        "annual_ret_pct": -4.704598013435235,
        "sharpe": -2.809882222668174,
        "max_dd_pct": 11.941113027467987,
        "win_rate_pct": 28.721804511278194,
        "profit_factor": 0.4240648237572835,
        "n_days": 665,
        "exposure_pct": 42.70676691729323,
        "hold_days": 3
      },
      "plate_vw_5d": {
        "total_ret_pct": -6.2721407834255505,
        "annual_ret_pct": -2.4247400376381623,
        "sharpe": -1.5845478885265907,
        "max_dd_pct": 7.134474643985292,
        "win_rate_pct": 27.06766917293233,
        "profit_factor": 0.6010431830267687,
        "n_days": 665,
        "exposure_pct": 38.64661654135338,
        "hold_days": 5
      },
      "plate_direction_1d": {
        "total_ret_pct": -70.89084292468448,
        "annual_ret_pct": -37.35369816995204,
        "sharpe": -1.1693116713535228,
        "max_dd_pct": 83.48165443441478,
        "win_rate_pct": 35.78947368421053,
        "profit_factor": 0.7926977799819911,
        "n_days": 665,
        "exposure_pct": 81.35338345864662,
        "hold_days": 1
      },
      "plate_direction_3d": {
        "total_ret_pct": -61.86730217983863,
        "annual_ret_pct": -30.60410175147007,
        "sharpe": -0.8720324458798607,
        "max_dd_pct": 77.32674255032704,
        "win_rate_pct": 38.045112781954884,
        "profit_factor": 0.8405598575405065,
        "n_days": 665,
        "exposure_pct": 81.35338345864662,
        "hold_days": 3
      },
      "plate_direction_5d": {
        "total_ret_pct": -84.15441806456101,
        "annual_ret_pct": -50.24836983707992,
        "sharpe": -1.8331360425320138,
        "max_dd_pct": 85.03716555801894,
        "win_rate_pct": 36.69172932330827,
        "profit_factor": 0.6921149952343124,
        "n_days": 665,
        "exposure_pct": 81.35338345864662,
        "hold_days": 5
      },
      "plate_dir+vol-wt_1d": {
        "total_ret_pct": -55.70460593485016,
        "annual_ret_pct": -26.550556337754273,
        "sharpe": -0.7094005911272633,
        "max_dd_pct": 77.99030849088298,
        "win_rate_pct": 37.29323308270677,
        "profit_factor": 0.8686513209840035,
        "n_days": 665,
        "exposure_pct": 81.35338345864662,
        "hold_days": 1
      },
      "plate_dir+vol-wt_3d": {
        "total_ret_pct": -57.56207787463018,
        "annual_ret_pct": -27.7332705987112,
        "sharpe": -0.75581661286044,
        "max_dd_pct": 66.31253472181733,
        "win_rate_pct": 38.64661654135338,
        "profit_factor": 0.8602309655067465,
        "n_days": 665,
        "exposure_pct": 81.35338345864662,
        "hold_days": 3
      },
      "plate_dir+vol-wt_5d": {
        "total_ret_pct": -70.92645419230932,
        "annual_ret_pct": -37.38275158570804,
        "sharpe": -1.1659511906467446,
        "max_dd_pct": 74.74392946256991,
        "win_rate_pct": 38.796992481203006,
        "profit_factor": 0.7919073081345875,
        "n_days": 665,
        "exposure_pct": 81.35338345864662,
        "hold_days": 5
      },
      "hybrid_1d": {
        "total_ret_pct": -60.869903900683674,
        "annual_ret_pct": -29.921776571966397,
        "sharpe": -1.557160916169911,
        "max_dd_pct": 64.07504921732364,
        "win_rate_pct": 18.195488721804512,
        "profit_factor": 0.6691244584621805,
        "n_days": 665,
        "exposure_pct": 52.03007518796993,
        "hold_days": 1
      },
      "hybrid_3d": {
        "total_ret_pct": -55.716879378792015,
        "annual_ret_pct": -26.558269148074352,
        "sharpe": -1.0600189934500464,
        "max_dd_pct": 60.23382577846882,
        "win_rate_pct": 26.31578947368421,
        "profit_factor": 0.7811104635829897,
        "n_days": 665,
        "exposure_pct": 59.3984962406015,
        "hold_days": 3
      },
      "hybrid_5d": {
        "total_ret_pct": -68.95811858996541,
        "annual_ret_pct": -35.80886644156376,
        "sharpe": -1.2590788181088932,
        "max_dd_pct": 72.3799578373527,
        "win_rate_pct": 27.518796992481203,
        "profit_factor": 0.742016270342346,
        "n_days": 665,
        "exposure_pct": 62.55639097744361,
        "hold_days": 5
      }
    },
    "SPY": {
      "always_sell_1d": {
        "total_ret_pct": 1.6077576152882633,
        "annual_ret_pct": 0.9261256845386701,
        "sharpe": 1.7283026024205503,
        "max_dd_pct": 0.6924645608836724,
        "win_rate_pct": 80.96330275229357,
        "profit_factor": 1.9489949221319116,
        "n_days": 436,
        "exposure_pct": 100.0,
        "hold_days": 1
      },
      "always_sell_3d": {
        "total_ret_pct": 1.6077576152882633,
        "annual_ret_pct": 0.9261256845386701,
        "sharpe": 1.7283026024205503,
        "max_dd_pct": 0.6924645608836724,
        "win_rate_pct": 80.96330275229357,
        "profit_factor": 1.9489949221319116,
        "n_days": 436,
        "exposure_pct": 100.0,
        "hold_days": 3
      },
      "always_sell_5d": {
        "total_ret_pct": 1.6077576152882633,
        "annual_ret_pct": 0.9261256845386701,
        "sharpe": 1.7283026024205503,
        "max_dd_pct": 0.6924645608836724,
        "win_rate_pct": 80.96330275229357,
        "profit_factor": 1.9489949221319116,
        "n_days": 436,
        "exposure_pct": 100.0,
        "hold_days": 5
      },
      "binary_1d": {
        "total_ret_pct": -19.73016251627908,
        "annual_ret_pct": -11.928979406458017,
        "sharpe": -6.514039012338326,
        "max_dd_pct": 19.73016251627908,
        "win_rate_pct": 33.715596330275226,
        "profit_factor": 0.08810676344768473,
        "n_days": 436,
        "exposure_pct": 56.42201834862385,
        "hold_days": 1
      },
      "binary_3d": {
        "total_ret_pct": -9.032694033543365,
        "annual_ret_pct": -5.32474643979628,
        "sharpe": -3.9501981968694606,
        "max_dd_pct": 9.032694033543365,
        "win_rate_pct": 39.22018348623853,
        "profit_factor": 0.1956390982625672,
        "n_days": 436,
        "exposure_pct": 54.58715596330275,
        "hold_days": 3
      },
      "binary_5d": {
        "total_ret_pct": -7.539015050025933,
        "annual_ret_pct": -4.429326496671459,
        "sharpe": -3.5213210918006665,
        "max_dd_pct": 7.539015050025933,
        "win_rate_pct": 39.908256880733944,
        "profit_factor": 0.20366452426070447,
        "n_days": 436,
        "exposure_pct": 53.899082568807344,
        "hold_days": 5
      },
      "plate_binary_1d": {
        "total_ret_pct": -19.719239201428785,
        "annual_ret_pct": -11.922052542173544,
        "sharpe": -6.515013700212899,
        "max_dd_pct": 19.719239201428785,
        "win_rate_pct": 33.02752293577982,
        "profit_factor": 0.08767291947450917,
        "n_days": 436,
        "exposure_pct": 55.5045871559633,
        "hold_days": 1
      },
      "plate_binary_3d": {
        "total_ret_pct": -9.576026391148751,
        "annual_ret_pct": -5.651996190779085,
        "sharpe": -4.108843180577557,
        "max_dd_pct": 9.576026391148751,
        "win_rate_pct": 38.53211009174312,
        "profit_factor": 0.18507576556667008,
        "n_days": 436,
        "exposure_pct": 54.12844036697248,
        "hold_days": 3
      },
      "plate_binary_5d": {
        "total_ret_pct": -8.099697345662893,
        "annual_ret_pct": -4.764719482558943,
        "sharpe": -3.6960165345941207,
        "max_dd_pct": 8.099697345662893,
        "win_rate_pct": 38.76146788990826,
        "profit_factor": 0.19027161824278005,
        "n_days": 436,
        "exposure_pct": 52.981651376146786,
        "hold_days": 5
      },
      "plate_vw_1d": {
        "total_ret_pct": -19.759634478297027,
        "annual_ret_pct": -11.947670615600458,
        "sharpe": -6.927998394848329,
        "max_dd_pct": 19.759634478297027,
        "win_rate_pct": 28.899082568807337,
        "profit_factor": 0.05191215379341701,
        "n_days": 436,
        "exposure_pct": 50.45871559633027,
        "hold_days": 1
      },
      "plate_vw_3d": {
        "total_ret_pct": -9.837904357514448,
        "annual_ret_pct": -5.810021927263421,
        "sharpe": -4.277950260353438,
        "max_dd_pct": 9.837904357514448,
        "win_rate_pct": 34.174311926605505,
        "profit_factor": 0.1276386399487778,
        "n_days": 436,
        "exposure_pct": 48.39449541284404,
        "hold_days": 3
      },
      "plate_vw_5d": {
        "total_ret_pct": -8.894670508046065,
        "annual_ret_pct": -5.241746200416064,
        "sharpe": -4.214584955638951,
        "max_dd_pct": 8.894670508046065,
        "win_rate_pct": 32.11009174311927,
        "profit_factor": 0.09182577624624588,
        "n_days": 436,
        "exposure_pct": 45.18348623853211,
        "hold_days": 5
      },
      "plate_direction_1d": {
        "total_ret_pct": -19.01256914784867,
        "annual_ret_pct": -11.474769545911535,
        "sharpe": -0.7222615885372946,
        "max_dd_pct": 30.06132213251374,
        "win_rate_pct": 27.06422018348624,
        "profit_factor": 0.8419309052651761,
        "n_days": 436,
        "exposure_pct": 69.03669724770643,
        "hold_days": 1
      },
      "plate_direction_3d": {
        "total_ret_pct": -9.474134797974742,
        "annual_ret_pct": -5.590563673232385,
        "sharpe": -0.3000425616548611,
        "max_dd_pct": 23.32198631485856,
        "win_rate_pct": 30.275229357798167,
        "profit_factor": 0.9304186023329771,
        "n_days": 436,
        "exposure_pct": 69.03669724770643,
        "hold_days": 3
      },
      "plate_direction_5d": {
        "total_ret_pct": 6.959256745824649,
        "annual_ret_pct": 3.96512628339063,
        "sharpe": 0.3307850128060183,
        "max_dd_pct": 14.750015093369134,
        "win_rate_pct": 30.963302752293576,
        "profit_factor": 1.0828292964302242,
        "n_days": 436,
        "exposure_pct": 69.03669724770643,
        "hold_days": 5
      },
      "plate_dir+vol-wt_1d": {
        "total_ret_pct": -28.37576460656709,
        "annual_ret_pct": -17.543036308797987,
        "sharpe": -1.1757721312563976,
        "max_dd_pct": 31.872974587859325,
        "win_rate_pct": 29.587155963302752,
        "profit_factor": 0.7532756062916022,
        "n_days": 436,
        "exposure_pct": 69.03669724770643,
        "hold_days": 1
      },
      "plate_dir+vol-wt_3d": {
        "total_ret_pct": -10.900138058313779,
        "annual_ret_pct": -6.453004482570146,
        "sharpe": -0.36230173731031723,
        "max_dd_pct": 24.222308782743397,
        "win_rate_pct": 32.11009174311927,
        "profit_factor": 0.9158760891125821,
        "n_days": 436,
        "exposure_pct": 69.03669724770643,
        "hold_days": 3
      },
      "plate_dir+vol-wt_5d": {
        "total_ret_pct": -11.169717788551125,
        "annual_ret_pct": -6.616698072648064,
        "sharpe": -0.3694411972060512,
        "max_dd_pct": 26.458618105237193,
        "win_rate_pct": 31.65137614678899,
        "profit_factor": 0.9143244063669127,
        "n_days": 436,
        "exposure_pct": 69.03669724770643,
        "hold_days": 5
      },
      "hybrid_1d": {
        "total_ret_pct": -18.973464723829604,
        "annual_ret_pct": -11.450066804702775,
        "sharpe": -0.8720718035950249,
        "max_dd_pct": 21.911592904909323,
        "win_rate_pct": 19.724770642201836,
        "profit_factor": 0.7666149778692598,
        "n_days": 436,
        "exposure_pct": 55.5045871559633,
        "hold_days": 1
      },
      "hybrid_3d": {
        "total_ret_pct": -1.8570367182779046,
        "annual_ret_pct": -1.077576467932173,
        "sharpe": -0.00910216097628334,
        "max_dd_pct": 19.807265696507883,
        "win_rate_pct": 24.770642201834864,
        "profit_factor": 0.997484011623248,
        "n_days": 436,
        "exposure_pct": 62.38532110091744,
        "hold_days": 3
      },
      "hybrid_5d": {
        "total_ret_pct": -6.047653042814439,
        "annual_ret_pct": -3.541365592354051,
        "sharpe": -0.17894328161877376,
        "max_dd_pct": 17.051577605891755,
        "win_rate_pct": 27.981651376146786,
        "profit_factor": 0.953178826208335,
        "n_days": 436,
        "exposure_pct": 62.61467889908256,
        "hold_days": 5
      }
    },
    "QQQ": {
      "always_sell_1d": {
        "total_ret_pct": 2.796429696794278,
        "annual_ret_pct": 1.6068721215513282,
        "sharpe": 2.435382226081701,
        "max_dd_pct": 0.814818021608649,
        "win_rate_pct": 81.65137614678899,
        "profit_factor": 2.2146098443178204,
        "n_days": 436,
        "exposure_pct": 100.0,
        "hold_days": 1
      },
      "always_sell_3d": {
        "total_ret_pct": 2.796429696794278,
        "annual_ret_pct": 1.6068721215513282,
        "sharpe": 2.435382226081701,
        "max_dd_pct": 0.814818021608649,
        "win_rate_pct": 81.65137614678899,
        "profit_factor": 2.2146098443178204,
        "n_days": 436,
        "exposure_pct": 100.0,
        "hold_days": 3
      },
      "always_sell_5d": {
        "total_ret_pct": 2.796429696794278,
        "annual_ret_pct": 1.6068721215513282,
        "sharpe": 2.435382226081701,
        "max_dd_pct": 0.814818021608649,
        "win_rate_pct": 81.65137614678899,
        "profit_factor": 2.2146098443178204,
        "n_days": 436,
        "exposure_pct": 100.0,
        "hold_days": 5
      },
      "binary_1d": {
        "total_ret_pct": -14.39688150595433,
        "annual_ret_pct": -8.592839197708713,
        "sharpe": -5.340776077116053,
        "max_dd_pct": 14.39688150595433,
        "win_rate_pct": 27.06422018348624,
        "profit_factor": 0.13225737453469094,
        "n_days": 436,
        "exposure_pct": 44.26605504587156,
        "hold_days": 1
      },
      "binary_3d": {
        "total_ret_pct": -9.93286666649067,
        "annual_ret_pct": -5.867373135548604,
        "sharpe": -4.196772635212332,
        "max_dd_pct": 9.93286666649067,
        "win_rate_pct": 27.522935779816514,
        "profit_factor": 0.1794892406457021,
        "n_days": 436,
        "exposure_pct": 42.6605504587156,
        "hold_days": 3
      },
      "binary_5d": {
        "total_ret_pct": -4.034511825170373,
        "annual_ret_pct": -2.352114670736427,
        "sharpe": -2.2097328212575094,
        "max_dd_pct": 4.460210597018829,
        "win_rate_pct": 34.174311926605505,
        "profit_factor": 0.38208747694228284,
        "n_days": 436,
        "exposure_pct": 44.95412844036697,
        "hold_days": 5
      },
      "plate_binary_1d": {
        "total_ret_pct": -15.466924424931994,
        "annual_ret_pct": -9.254989681870363,
        "sharpe": -5.63084619238998,
        "max_dd_pct": 15.466924424931994,
        "win_rate_pct": 25.688073394495415,
        "profit_factor": 0.11972910224637469,
        "n_days": 436,
        "exposure_pct": 43.80733944954128,
        "hold_days": 1
      },
      "plate_binary_3d": {
        "total_ret_pct": -10.008739843125236,
        "annual_ret_pct": -5.9132140612607405,
        "sharpe": -4.233373594849653,
        "max_dd_pct": 10.008739843125236,
        "win_rate_pct": 26.146788990825687,
        "profit_factor": 0.17293547703306386,
        "n_days": 436,
        "exposure_pct": 41.284403669724774,
        "hold_days": 3
      },
      "plate_binary_5d": {
        "total_ret_pct": -4.15709120181077,
        "annual_ret_pct": -2.424224810167619,
        "sharpe": -2.2734562165791115,
        "max_dd_pct": 4.582246216824532,
        "win_rate_pct": 32.11009174311927,
        "profit_factor": 0.3641325633654546,
        "n_days": 436,
        "exposure_pct": 42.6605504587156,
        "hold_days": 5
      },
      "plate_vw_1d": {
        "total_ret_pct": -18.408136140011177,
        "annual_ret_pct": -11.093502205878314,
        "sharpe": -6.149352435822107,
        "max_dd_pct": 18.408136140011177,
        "win_rate_pct": 22.706422018348622,
        "profit_factor": 0.08179754250598055,
        "n_days": 436,
        "exposure_pct": 42.6605504587156,
        "hold_days": 1
      },
      "plate_vw_3d": {
        "total_ret_pct": -8.609945324284507,
        "annual_ret_pct": -5.070694603916303,
        "sharpe": -3.931405577776794,
        "max_dd_pct": 8.609945324284507,
        "win_rate_pct": 23.853211009174313,
        "profit_factor": 0.1654623580406694,
        "n_days": 436,
        "exposure_pct": 37.15596330275229,
        "hold_days": 3
      },
      "plate_vw_5d": {
        "total_ret_pct": -5.272997601205997,
        "annual_ret_pct": -3.082481716265628,
        "sharpe": -2.807337952886186,
        "max_dd_pct": 5.272997601205997,
        "win_rate_pct": 26.605504587155966,
        "profit_factor": 0.25889739158542396,
        "n_days": 436,
        "exposure_pct": 36.00917431192661,
        "hold_days": 5
      },
      "plate_direction_1d": {
        "total_ret_pct": -13.290210311113348,
        "annual_ret_pct": -7.911686975131749,
        "sharpe": -0.35129214764270267,
        "max_dd_pct": 26.75772045416178,
        "win_rate_pct": 31.422018348623855,
        "profit_factor": 0.9231577861746618,
        "n_days": 436,
        "exposure_pct": 69.03669724770643,
        "hold_days": 1
      },
      "plate_direction_3d": {
        "total_ret_pct": -0.4301554469590907,
        "annual_ret_pct": -0.2488480829667683,
        "sharpe": 0.08078643902876823,
        "max_dd_pct": 18.53299406095145,
        "win_rate_pct": 34.862385321100916,
        "profit_factor": 1.018705082524248,
        "n_days": 436,
        "exposure_pct": 69.03669724770643,
        "hold_days": 3
      },
      "plate_direction_5d": {
        "total_ret_pct": -4.525935175872064,
        "annual_ret_pct": -2.641440873949541,
        "sharpe": -0.05128169334579238,
        "max_dd_pct": 19.156734675946915,
        "win_rate_pct": 34.403669724770644,
        "profit_factor": 0.9882751787937994,
        "n_days": 436,
        "exposure_pct": 69.03669724770643,
        "hold_days": 5
      },
      "plate_dir+vol-wt_1d": {
        "total_ret_pct": -23.536593821664443,
        "annual_ret_pct": -14.367555327424796,
        "sharpe": -0.7404508656079608,
        "max_dd_pct": 33.12496938928254,
        "win_rate_pct": 30.504587155963304,
        "profit_factor": 0.8459526578294086,
        "n_days": 436,
        "exposure_pct": 69.03669724770643,
        "hold_days": 1
      },
      "plate_dir+vol-wt_3d": {
        "total_ret_pct": 17.777481380535896,
        "annual_ret_pct": 9.91897857821149,
        "sharpe": 0.6047093782138112,
        "max_dd_pct": 21.952102104837607,
        "win_rate_pct": 34.403669724770644,
        "profit_factor": 1.149125012545728,
        "n_days": 436,
        "exposure_pct": 69.03669724770643,
        "hold_days": 3
      },
      "plate_dir+vol-wt_5d": {
        "total_ret_pct": -19.788144549592733,
        "annual_ret_pct": -11.965754547828189,
        "sharpe": -0.5906819239047117,
        "max_dd_pct": 26.50984261309829,
        "win_rate_pct": 33.25688073394495,
        "profit_factor": 0.8735868620287763,
        "n_days": 436,
        "exposure_pct": 69.03669724770643,
        "hold_days": 5
      },
      "hybrid_1d": {
        "total_ret_pct": -20.563567659667047,
        "annual_ret_pct": -12.458650158247341,
        "sharpe": -1.2003608653319096,
        "max_dd_pct": 23.31341530268084,
        "win_rate_pct": 15.59633027522936,
        "profit_factor": 0.7350477227239842,
        "n_days": 436,
        "exposure_pct": 43.80733944954128,
        "hold_days": 1
      },
      "hybrid_3d": {
        "total_ret_pct": 3.0241648009833755,
        "annual_ret_pct": 1.7369148966576597,
        "sharpe": 0.20481325498559316,
        "max_dd_pct": 20.152208899326016,
        "win_rate_pct": 22.477064220183486,
        "profit_factor": 1.0508330547315061,
        "n_days": 436,
        "exposure_pct": 50.0,
        "hold_days": 3
      },
      "hybrid_5d": {
        "total_ret_pct": -8.279448625497654,
        "annual_ret_pct": -4.872427079924568,
        "sharpe": -0.28071639374510443,
        "max_dd_pct": 19.24599839544091,
        "win_rate_pct": 22.93577981651376,
        "profit_factor": 0.9337191016985237,
        "n_days": 436,
        "exposure_pct": 53.669724770642205,
        "hold_days": 5
      }
    }
  }
}